tests/__init__.py
tests/test_access_token.py
tests/test_address.py
tests/test_bank_info.py
tests/test_blob.py
tests/test_member_registration.py
tests/test_profile.py
tests/test_token_request.py
tests/test_trusted_benificiary.py
tests/utils.py
tokenio/__init__.py
tokenio/access_token_builder.py
tokenio/account.py
tokenio/config.py
tokenio/exceptions.py
tokenio/member.py
tokenio/token_client.py
tokenio/token_request.py
tokenio/transfer_token_builder.py
tokenio/utils.py
tokenio/proto/__init__.py
tokenio/proto/account_pb2.py
tokenio/proto/account_pb2_grpc.py
tokenio/proto/address_pb2.py
tokenio/proto/address_pb2_grpc.py
tokenio/proto/alias_pb2.py
tokenio/proto/alias_pb2_grpc.py
tokenio/proto/bankinfo_pb2.py
tokenio/proto/bankinfo_pb2_grpc.py
tokenio/proto/banklink_pb2.py
tokenio/proto/banklink_pb2_grpc.py
tokenio/proto/bankstatus_pb2.py
tokenio/proto/bankstatus_pb2_grpc.py
tokenio/proto/blob_pb2.py
tokenio/proto/blob_pb2_grpc.py
tokenio/proto/member_pb2.py
tokenio/proto/member_pb2_grpc.py
tokenio/proto/money_pb2.py
tokenio/proto/money_pb2_grpc.py
tokenio/proto/notification_pb2.py
tokenio/proto/notification_pb2_grpc.py
tokenio/proto/pricing_pb2.py
tokenio/proto/pricing_pb2_grpc.py
tokenio/proto/providerspecific_pb2.py
tokenio/proto/providerspecific_pb2_grpc.py
tokenio/proto/security_pb2.py
tokenio/proto/security_pb2_grpc.py
tokenio/proto/subscriber_pb2.py
tokenio/proto/subscriber_pb2_grpc.py
tokenio/proto/token_pb2.py
tokenio/proto/token_pb2_grpc.py
tokenio/proto/transaction_pb2.py
tokenio/proto/transaction_pb2_grpc.py
tokenio/proto/transfer_pb2.py
tokenio/proto/transfer_pb2_grpc.py
tokenio/proto/transferinstructions_pb2.py
tokenio/proto/transferinstructions_pb2_grpc.py
tokenio/proto/extensions/__init__.py
tokenio/proto/extensions/field_pb2.py
tokenio/proto/extensions/field_pb2_grpc.py
tokenio/proto/extensions/message_pb2.py
tokenio/proto/extensions/message_pb2_grpc.py
tokenio/proto/extensions/service_pb2.py
tokenio/proto/extensions/service_pb2_grpc.py
TokenIO-0.0.1a3.dist-info/LICENSE
TokenIO-0.0.1a3.dist-info/METADATA
TokenIO-0.0.1a3.dist-info/WHEEL
TokenIO-0.0.1a3.dist-info/top_level.txt
TokenIO-0.0.1a3.dist-info/RECORD
